dbqna/__init__.py
dbqna/db_helper.py
dbqna/dbqna.py
AIDBBot-0.1.2.dist-info/LICENSE
AIDBBot-0.1.2.dist-info/METADATA
AIDBBot-0.1.2.dist-info/WHEEL
AIDBBot-0.1.2.dist-info/top_level.txt
AIDBBot-0.1.2.dist-info/RECORD
